repoindex/__init__.py
repoindex/__main__.py
repoindex/analytics_store.py
repoindex/api.py
repoindex/citation.py
repoindex/cli.py
repoindex/cli_utils.py
repoindex/config.py
repoindex/core.py
repoindex/cran.py
repoindex/events.py
repoindex/exit_codes.py
repoindex/format_utils.py
repoindex/ghops.py
repoindex/gitignore.py
repoindex/metadata.py
repoindex/output.py
repoindex/progress.py
repoindex/pypi.py
repoindex/query.py
repoindex/render.py
repoindex/repo_filter.py
repoindex/status.py
repoindex/tags.py
repoindex/utils.py
repoindex/version_manager.py
repoindex/vfs_utils.py
repoindex/commands/__init__.py
repoindex/commands/catalog.py
repoindex/commands/claude.py
repoindex/commands/config.py
repoindex/commands/config_excludes.py
repoindex/commands/config_repos.py
repoindex/commands/copy.py
repoindex/commands/events.py
repoindex/commands/export.py
repoindex/commands/link.py
repoindex/commands/ops.py
repoindex/commands/query.py
repoindex/commands/refresh.py
repoindex/commands/shell.py
repoindex/commands/status.py
repoindex/commands/tag.py
repoindex/commands/view.py
repoindex/database/__init__.py
repoindex/database/connection.py
repoindex/database/errors.py
repoindex/database/events.py
repoindex/database/query_compiler.py
repoindex/database/repository.py
repoindex/database/schema.py
repoindex/domain/__init__.py
repoindex/domain/event.py
repoindex/domain/operation.py
repoindex/domain/repository.py
repoindex/domain/tag.py
repoindex/domain/view.py
repoindex/git_ops/__init__.py
repoindex/git_ops/utils.py
repoindex/infra/__init__.py
repoindex/infra/file_store.py
repoindex/infra/git_client.py
repoindex/infra/github_client.py
repoindex/infra/zenodo_client.py
repoindex/services/__init__.py
repoindex/services/boilerplate_service.py
repoindex/services/copy_service.py
repoindex/services/event_service.py
repoindex/services/export_service.py
repoindex/services/git_ops_service.py
repoindex/services/link_service.py
repoindex/services/repository_service.py
repoindex/services/tag_service.py
repoindex-0.10.2.dist-info/METADATA
repoindex-0.10.2.dist-info/WHEEL
repoindex-0.10.2.dist-info/entry_points.txt
repoindex-0.10.2.dist-info/RECORD
